pisurveillance/__init__.py
pisurveillance/config.py
pisurveillance/main.py
pisurveillance/surveillance.py
pisurveillance-0.1.6.dist-info/METADATA
pisurveillance-0.1.6.dist-info/WHEEL
pisurveillance-0.1.6.dist-info/entry_points.txt
pisurveillance-0.1.6.dist-info/RECORD
