Metadata-Version: 2.3
Name: pisurveillance
Version: 0.1.6
Summary: 
Author: pshrestha
Author-email: pranaya.shrestha2@gmail.com
Requires-Python: >=3.10
Classifier: Programming Language :: Python :: 3
Classifier: Programming Language :: Python :: 3.10
Classifier: Programming Language :: Python :: 3.11
Classifier: Programming Language :: Python :: 3.12
Classifier: Programming Language :: Python :: 3.13
Requires-Dist: aiohttp (>=3.11.18,<4.0.0)
Requires-Dist: dotenv (>=0.9.9,<0.10.0)
Requires-Dist: picamera2 (>=0.3.27,<0.4.0) ; sys_platform == "linux"
